hacs_registry/__init__.py
hacs_registry/agent_registry.py
hacs_registry/exceptions.py
hacs_registry/iam_registry.py
hacs_registry/integration.py
hacs_registry/persistence_integration.py
hacs_registry/plugin_discovery.py
hacs_registry/py.typed
hacs_registry/resource_registry.py
hacs_registry/tool_registry.py
hacs_registry/validation.py
hacs_registry/versioning.py
hacs_registry/core/__init__.py
hacs_registry/core/base.py
hacs_registry/core/events.py
hacs_registry/core/exceptions.py
hacs_registry/core/lifecycle.py
hacs_registry/domain/__init__.py
hacs_registry/domain/models/__init__.py
hacs_registry/domain/models/resource.py
hacs_registry/domain/services/__init__.py
hacs_registry/domain/services/resource_service.py
hacs_registry/infrastructure/__init__.py
hacs_registry/infrastructure/integration/__init__.py
hacs_registry/infrastructure/integration/framework_adapter.py
hacs_registry/infrastructure/integration/langchain_adapter.py
hacs_registry/infrastructure/integration/mcp_adapter.py
hacs_registry/infrastructure/monitoring/__init__.py
hacs_registry/infrastructure/monitoring/audit_logger.py
hacs_registry/infrastructure/monitoring/compliance_monitor.py
hacs_registry/infrastructure/monitoring/metrics_collector.py
hacs_registry-0.4.3.dist-info/METADATA
hacs_registry-0.4.3.dist-info/WHEEL
hacs_registry-0.4.3.dist-info/RECORD
